{
  "administrative_area_level_1": "UPRAVNO-ADMINISTRATIVNI PROSTOR PODJETJA ALI DRUGE ORGANIZACIJE",
  "administrative_area_level_2": "UPRAVNO-ADMINISTRATIVNI PROSTOR PODJETJA ALI DRUGE ORGANIZACIJE",
  "administrative_area_level_3": "UPRAVNO-ADMINISTRATIVNI PROSTOR PODJETJA ALI DRUGE ORGANIZACIJE",
  "administrative_area_level_4": "UPRAVNO-ADMINISTRATIVNI PROSTOR PODJETJA ALI DRUGE ORGANIZACIJE",
  "administrative_area_level_5": "UPRAVNO-ADMINISTRATIVNI PROSTOR PODJETJA ALI DRUGE ORGANIZACIJE",
  "administrative_area_level_6": "UPRAVNO-ADMINISTRATIVNI PROSTOR PODJETJA ALI DRUGE ORGANIZACIJE",
  "administrative_area_level_7": "UPRAVNO-ADMINISTRATIVNI PROSTOR PODJETJA ALI DRUGE ORGANIZACIJE",
  "archipelago": "NARAVNA POVRŠINA",
  "colloquial_area": "PROSTOR DRUGIH USTANOV",
  "continent": "NARAVNA POVRŠINA",
  "country": "NARAVNA POVRŠINA",
  "establishment": "PROSTOR DRUGIH USTANOV",
  "finance": "PROSTOR ZA DENARNO-FINANČNE STORITVE",
  "floor": "NASTANITVENI PROSTOR Z NEPOSREDNO OKOLICO (DVORIŠČE, VRT IPD.)",
  "food": "PROSTOR ZA ŠPORT, REKREACIJO, ZABAVO",
  "general_contractor": "UPRAVNO-ADMINISTRATIVNI PROSTOR PODJETJA ALI DRUGE ORGANIZACIJE",
  "geocode": "NARAVNA POVRŠINA",
  "health": "PROSTOR ZA ZDRAVSTVENE STORITVE Z NEPOSRED. OKOLICO (DVORIŠČE IPD.)",
  "intersection": "OBMOČJE PROMETA",
  "landmark": "NARAVNA POVRŠINA",
  "locality": "NASTANITVENI PROSTOR Z NEPOSREDNO OKOLICO (DVORIŠČE, VRT IPD.)",
  "natural_feature": "NARAVNA POVRŠINA",
  "neighborhood": "NASTANITVENI PROSTOR Z NEPOSREDNO OKOLICO (DVORIŠČE, VRT IPD.)",
  "place_of_worship": "PROSTOR ZA VERSKE OBREDE",
  "plus_code": "NASTANITVENI PROSTOR Z NEPOSREDNO OKOLICO (DVORIŠČE, VRT IPD.)",
  "point_of_interest": "PROSTOR ZA KULTURNO DEJAVNOST",
  "political": "PROSTOR DRŽ. USTANOVE, ORGANA LOKALNE SKUP., POLIT. ALI INTERES. ORG.",
  "post_box": "NASTANITVENI PROSTOR Z NEPOSREDNO OKOLICO (DVORIŠČE, VRT IPD.)",
  "postal_code": "NASTANITVENI PROSTOR Z NEPOSREDNO OKOLICO (DVORIŠČE, VRT IPD.)",
  "postal_code_prefix": "NASTANITVENI PROSTOR Z NEPOSREDNO OKOLICO (DVORIŠČE, VRT IPD.)",
  "postal_code_suffix": "NASTANITVENI PROSTOR Z NEPOSREDNO OKOLICO (DVORIŠČE, VRT IPD.)",
  "postal_town": "NASTANITVENI PROSTOR Z NEPOSREDNO OKOLICO (DVORIŠČE, VRT IPD.)",
  "premise": "NASTANITVENI PROSTOR Z NEPOSREDNO OKOLICO (DVORIŠČE, VRT IPD.)",
  "room": "NASTANITVENI PROSTOR Z NEPOSREDNO OKOLICO (DVORIŠČE, VRT IPD.)",
  "route": "OBMOČJE PROMETA",
  "street_address": "NASTANITVENI PROSTOR Z NEPOSREDNO OKOLICO (DVORIŠČE, VRT IPD.)",
  "street_number": "NASTANITVENI PROSTOR Z NEPOSREDNO OKOLICO (DVORIŠČE, VRT IPD.)",
  "sublocality": "NASTANITVENI PROSTOR Z NEPOSREDNO OKOLICO (DVORIŠČE, VRT IPD.)",
  "sublocality_level_1": "OBMOČJE PROMETA",
  "sublocality_level_2": "OBMOČJE PROMETA",
  "sublocality_level_3": "OBMOČJE PROMETA",
  "sublocality_level_4": "OBMOČJE PROMETA",
  "sublocality_level_5": "OBMOČJE PROMETA",
  "subpremise": "NASTANITVENI PROSTOR Z NEPOSREDNO OKOLICO (DVORIŠČE, VRT IPD.)",
  "town_square": "PROSTOR ZA ŠPORT, REKREACIJO, ZABAVO",
  "accounting": "UPRAVNO-ADMINISTRATIVNI PROSTOR PODJETJA ALI DRUGE ORGANIZACIJE",
  "airport": "OBMOČJE PROMETA",
  "amusement_park": "PROSTOR ZA ŠPORT, REKREACIJO, ZABAVO",
  "aquarium": "PROSTOR ZA ŠPORT, REKREACIJO, ZABAVO",
  "art_gallery": "PROSTOR ZA KULTURNO DEJAVNOST",
  "atm": "PROSTOR ZA DENARNO-FINANČNE STORITVE",
  "bakery": "PRODAJNI PROSTOR",
  "bank": "PROSTOR ZA DENARNO-FINANČNE STORITVE",
  "bar": "PROSTOR ZA ŠPORT, REKREACIJO, ZABAVO",
  "beauty_salon": "PROSTOR ZA ŠPORT, REKREACIJO, ZABAVO",
  "bicycle_store": "PRODAJNI PROSTOR",
  "book_store": "PRODAJNI PROSTOR",
  "bowling_alley": "PROSTOR ZA ŠPORT, REKREACIJO, ZABAVO",
  "bus_station": "OBMOČJE PROMETA",
  "cafe": "PRODAJNI PROSTOR",
  "campground": "NARAVNA POVRŠINA",
  "car_dealer": "PRODAJNI PROSTOR",
  "car_rental": "PROSTOR DRUGIH USTANOV",
  "car_repair": "PROSTOR DRUGIH USTANOV",
  "car_wash": "PROSTOR DRUGIH USTANOV",
  "casino": "PROSTOR DRUGIH USTANOV",
  "cemetery": "PROSTOR ZA VERSKE OBREDE",
  "church": "PROSTOR ZA VERSKE OBREDE",
  "city_hall": "PROSTOR DRŽ. USTANOVE, ORGANA LOKALNE SKUP., POLIT. ALI INTERES. ORG.",
  "clothing_store": "PRODAJNI PROSTOR",
  "convenience_store": "PRODAJNI PROSTOR",
  "courthouse": "PROSTOR DRŽ. USTANOVE, ORGANA LOKALNE SKUP., POLIT. ALI INTERES. ORG.",
  "dentist": "PROSTOR ZA ZDRAVSTVENE STORITVE Z NEPOSRED. OKOLICO (DVORIŠČE IPD.)",
  "department_store": "PRODAJNI PROSTOR",
  "doctor": "PROSTOR ZA ZDRAVSTVENE STORITVE Z NEPOSRED. OKOLICO (DVORIŠČE IPD.)",
  "drugstore": "PROSTOR ZA ZDRAVSTVENE STORITVE Z NEPOSRED. OKOLICO (DVORIŠČE IPD.)",
  "electrician": "PROSTOR DRUGIH USTANOV",
  "electronics_store": "PRODAJNI PROSTOR",
  "embassy": "PROSTOR DRŽ. USTANOVE, ORGANA LOKALNE SKUP., POLIT. ALI INTERES. ORG.",
  "fire_station": "KOMUNALNI PROSTOR",
  "florist": "PROSTOR DRUGIH USTANOV",
  "funeral_home": "PROSTOR ZA VERSKE OBREDE",
  "furniture_store": "PRODAJNI PROSTOR",
  "gas_station": "PRODAJNI PROSTOR",
  "gym": "PROSTOR ZA ŠPORT, REKREACIJO, ZABAVO",
  "hair_care": "PRODAJNI PROSTOR",
  "hardware_store": "PRODAJNI PROSTOR",
  "hindu_temple": "PROSTOR ZA VERSKE OBREDE",
  "home_goods_store": "PRODAJNI PROSTOR",
  "hospital": "PROSTOR ZA ZDRAVSTVENE STORITVE Z NEPOSRED. OKOLICO (DVORIŠČE IPD.)",
  "insurance_agency": "PROSTOR ZA INDUSTRIJSKO, KMETIJSKO ALI OBRTNO PROIZVODNJO IN STORITVE",
  "jewelry_store": "PRODAJNI PROSTOR",
  "laundry": "PROSTOR ZA INDUSTRIJSKO, KMETIJSKO ALI OBRTNO PROIZVODNJO IN STORITVE",
  "lawyer": "PROSTOR ZA INDUSTRIJSKO, KMETIJSKO ALI OBRTNO PROIZVODNJO IN STORITVE",
  "library": "PROST. ZA VZGOJNOVAR. IN IZOBR. DEJ. Z NEPOS. OKOL.(DVORIŠČE,ŠOL.IGR.)",
  "light_rail_station": "OBMOČJE PROMETA",
  "liquor_store": "PRODAJNI PROSTOR",
  "local_government_office": "PROSTOR DRŽ. USTANOVE, ORGANA LOKALNE SKUP., POLIT. ALI INTERES. ORG.",
  "locksmith": "PROSTOR ZA INDUSTRIJSKO, KMETIJSKO ALI OBRTNO PROIZVODNJO IN STORITVE",
  "lodging": "NASTANITVENI PROSTOR Z NEPOSREDNO OKOLICO (DVORIŠČE, VRT IPD.)",
  "meal_delivery": "PROSTOR ZA INDUSTRIJSKO, KMETIJSKO ALI OBRTNO PROIZVODNJO IN STORITVE",
  "meal_takeaway": "PRODAJNI PROSTOR",
  "mosque": "PROSTOR ZA VERSKE OBREDE",
  "movie_rental": "PROSTOR ZA INDUSTRIJSKO, KMETIJSKO ALI OBRTNO PROIZVODNJO IN STORITVE",
  "movie_theater": "PROSTOR ZA ŠPORT, REKREACIJO, ZABAVO",
  "moving_company": "PROSTOR ZA INDUSTRIJSKO, KMETIJSKO ALI OBRTNO PROIZVODNJO IN STORITVE",
  "museum": "PROSTOR ZA KULTURNO DEJAVNOST",
  "night_club": "PROSTOR ZA ŠPORT, REKREACIJO, ZABAVO",
  "painter": "PROSTOR ZA INDUSTRIJSKO, KMETIJSKO ALI OBRTNO PROIZVODNJO IN STORITVE",
  "park": "PROSTOR ZA ŠPORT, REKREACIJO, ZABAVO",
  "parking": "OBMOČJE PROMETA",
  "pet_store": "PRODAJNI PROSTOR",
  "pharmacy": "PROSTOR ZA ZDRAVSTVENE STORITVE Z NEPOSRED. OKOLICO (DVORIŠČE IPD.)",
  "physiotherapist": "PROSTOR ZA ZDRAVSTVENE STORITVE Z NEPOSRED. OKOLICO (DVORIŠČE IPD.)",
  "plumber": "PROSTOR ZA INDUSTRIJSKO, KMETIJSKO ALI OBRTNO PROIZVODNJO IN STORITVE",
  "police": "URADNI PROSTORI POLICIJE",
  "post_office": "PROSTOR ZA INDUSTRIJSKO, KMETIJSKO ALI OBRTNO PROIZVODNJO IN STORITVE",
  "primary_school": "PROST. ZA VZGOJNOVAR. IN IZOBR. DEJ. Z NEPOS. OKOL.(DVORIŠČE,ŠOL.IGR.)",
  "real_estate_agency": "PROSTOR ZA INDUSTRIJSKO, KMETIJSKO ALI OBRTNO PROIZVODNJO IN STORITVE",
  "restaurant": "PROSTOR ZA ŠPORT, REKREACIJO, ZABAVO",
  "roofing_contractor": "PROSTOR ZA INDUSTRIJSKO, KMETIJSKO ALI OBRTNO PROIZVODNJO IN STORITVE",
  "rv_park": "NASTANITVENI PROSTOR Z NEPOSREDNO OKOLICO (DVORIŠČE, VRT IPD.)",
  "school": "PROST. ZA VZGOJNOVAR. IN IZOBR. DEJ. Z NEPOS. OKOL.(DVORIŠČE,ŠOL.IGR.)",
  "secondary_school": "PROST. ZA VZGOJNOVAR. IN IZOBR. DEJ. Z NEPOS. OKOL.(DVORIŠČE,ŠOL.IGR.)",
  "shoe_store": "PRODAJNI PROSTOR",
  "shopping_mall": "PRODAJNI PROSTOR",
  "spa": "PROSTOR ZA INDUSTRIJSKO, KMETIJSKO ALI OBRTNO PROIZVODNJO IN STORITVE",
  "stadium": "PROSTOR ZA ŠPORT, REKREACIJO, ZABAVO",
  "storage": "PROSTOR ZA INDUSTRIJSKO, KMETIJSKO ALI OBRTNO PROIZVODNJO IN STORITVE",
  "store": "PRODAJNI PROSTOR",
  "subway_station": "OBMOČJE PROMETA",
  "supermarket": "PRODAJNI PROSTOR",
  "synagogue": "PROSTOR ZA VERSKE OBREDE",
  "taxi_stand": "OBMOČJE PROMETA",
  "tourist_attraction": "PROSTOR ZA KULTURNO DEJAVNOST",
  "train_station": "OBMOČJE PROMETA",
  "transit_station": "OBMOČJE PROMETA",
  "travel_agency": "PROSTOR ZA INDUSTRIJSKO, KMETIJSKO ALI OBRTNO PROIZVODNJO IN STORITVE",
  "university": "PROST. ZA VZGOJNOVAR. IN IZOBR. DEJ. Z NEPOS. OKOL.(DVORIŠČE,ŠOL.IGR.)",
  "veterinary_care": "PROSTOR ZA ZDRAVSTVENE STORITVE Z NEPOSRED. OKOLICO (DVORIŠČE IPD.)",
  "zoo": "PROSTOR ZA ŠPORT, REKREACIJO, ZABAVO"
}
